nester.py
jas_nester-1.3.0.dist-info/METADATA
jas_nester-1.3.0.dist-info/WHEEL
jas_nester-1.3.0.dist-info/top_level.txt
jas_nester-1.3.0.dist-info/RECORD
