Metadata-Version: 2.1
Name: jas-nester
Version: 1.3.0
Summary: This function takes a positional argument called “the_list",
Author: Jjhar Singh
Author-email: sage_r3vok@icloud.com
